dify/__init__.py
dify/exceptions.py
dify/http.py
dify/schemas.py
dify/app/__init__.py
dify/app/schemas.py
dify/app/utils.py
dify/app/conversation/__init__.py
dify/app/conversation/schemas.py
dify/app/workflow/__init__.py
dify/app/workflow/schemas.py
dify/dataset/__init__.py
dify/dataset/schemas.py
dify/file/__init__.py
dify/file/schemas.py
dify/llm/__init__.py
dify/llm/schemas.py
dify/tag/__init__.py
dify/tag/schemas.py
dify/tool/__init__.py
dify/tool/schemas.py
dify_sdk-0.1.27.dist-info/METADATA
dify_sdk-0.1.27.dist-info/WHEEL
dify_sdk-0.1.27.dist-info/licenses/LICENSE
dify_sdk-0.1.27.dist-info/RECORD
