Metadata-Version: 2.4
Name: dify-sdk
Version: 0.1.27
Summary: Dify SDK for Python
Project-URL: Homepage, https://github.com/cruldra/dify-sdk
Project-URL: Bug Tracker, https://github.com/cruldra/dify-sdk/issues
Author-email: cruldra <cruldra@gmail.com>
License: MIT
License-File: LICENSE
Classifier: License :: OSI Approved :: MIT License
Classifier: Operating System :: OS Independent
Classifier: Programming Language :: Python :: 3
Requires-Python: >=3.12
Requires-Dist: dotenv>=0.9.9
Requires-Dist: httpx>=0.28.1
Requires-Dist: pydantic>=2.10.6
Provides-Extra: dev
Requires-Dist: pytest-asyncio>=0.22.0; extra == 'dev'
Requires-Dist: pytest-mock>=3.14.0; extra == 'dev'
Requires-Dist: pytest>=6.0; extra == 'dev'
Requires-Dist: ruff>=0.0.254; extra == 'dev'
